[{"id":"10","BVN":"21273676399","Firstname":"Alimi","Middlename":"Azeez","Lastname":"Tobi","Branch":"Ikeja","Product":"Market Weekly","Loan_Amount":"200000","Interest_Amt":"6000","Total_Bal":"206000","Officer_Name":"John Smith","Date_Disbursed":"2025-12-07","Status":"Active"},{"id":"5","BVN":"22388291021","Firstname":"Ibrahim","Middlename":"Akanji","Lastname":"Sulaimon","Branch":"Ikeja","Product":"Maketplus Daily","Loan_Amount":"450000","Interest_Amt":"0","Total_Bal":"423000","Officer_Name":"John Smith","Date_Disbursed":"2025-11-30","Status":"Active"}]